kwikapi/tornado/__init__.py
kwikapi/tornado/kwikapi_tornado.py
kwikapi_tornado-0.3.8.dist-info/LICENSE
kwikapi_tornado-0.3.8.dist-info/METADATA
kwikapi_tornado-0.3.8.dist-info/WHEEL
kwikapi_tornado-0.3.8.dist-info/top_level.txt
kwikapi_tornado-0.3.8.dist-info/RECORD
