Metadata-Version: 2.1
Name: kwikapi-tornado
Version: 0.3.8
Summary: Quickest way to build powerful HTTP APIs in Python
Home-page: https://github.com/deep-compute/kwikapi.tornado
Author: Deep Compute, LLC
Author-email: contact@deepcompute.com
License: MIT License
Download-URL: https://github.com/deep-compute/kwikapi.tornado/tarball/0.3.8
Platform: UNKNOWN
Classifier: Environment :: Web Environment
Classifier: Intended Audience :: Developers
Classifier: License :: OSI Approved :: MIT License
Classifier: Operating System :: OS Independent
Classifier: Programming Language :: Python
Classifier: Programming Language :: Python :: 3
Classifier: Programming Language :: Python :: 3.5
Classifier: Topic :: Internet :: WWW/HTTP
Classifier: Topic :: Internet :: WWW/HTTP :: Dynamic Content
Requires-Dist: tornado (==5.0.2)
Requires-Dist: deeputil (==0.2.9)
Requires-Dist: requests (==2.20.0)
